src/__init__.py
src/betterstar.py
betterstar-1.0.2.dist-info/LICENSE
betterstar-1.0.2.dist-info/METADATA
betterstar-1.0.2.dist-info/WHEEL
betterstar-1.0.2.dist-info/top_level.txt
betterstar-1.0.2.dist-info/RECORD
