Metadata-Version: 2.1
Name: betterstar
Version: 1.0.2
Summary: A better looking star marker for matplotlib plots.
Home-page: https://github.com/muederotter/betterstar
Author: Ole Meiforth
Classifier: Programming Language :: Python :: 3
Classifier: License :: OSI Approved :: MIT License
Classifier: Operating System :: OS Independent
Requires-Python: >=3.6
License-File: LICENSE
Requires-Dist: numpy
Requires-Dist: matplotlib
